src/__init__.py
src/__main__.py
src/index.py
src/utils/__init__.py
src/utils/util.py
hola_dev-0.0.8.dist-info/LICENSE
hola_dev-0.0.8.dist-info/METADATA
hola_dev-0.0.8.dist-info/WHEEL
hola_dev-0.0.8.dist-info/entry_points.txt
hola_dev-0.0.8.dist-info/top_level.txt
hola_dev-0.0.8.dist-info/RECORD
