Metadata-Version: 2.1
Name: hola-dev
Version: 0.0.8
Summary: Common packages installer on MAC
Home-page: https://github.com/JunBeum-Cho/hola-dev
Download-URL: https://github.com/user/reponame/archive/v_01.tar.gz
Author: JunBeum Cho
Author-email: ahengksk@gmail.com
Keywords: mac,package installers
License-File: LICENSE
Requires-Dist: requests
Requires-Dist: selenium
Requires-Dist: inquirerpy
Requires-Dist: fake-useragent
Requires-Dist: webdriver-manager
Requires-Dist: python-dotenv
Requires-Dist: boto3
Requires-Dist: yachalk
